{"api_api.md":"BxItkGly","api_contact.md":"_Udi5NYX","api_index.md":"OoTBKbn4","api_message.md":"DtuNaHZe","api_standard.md":"C6n9yBCD","event_general-data.md":"CmCazGvT","event_index.md":"DlZK1tMO","event_message.md":"C7UcKrhK","event_notice.md":"BNABVtu3","event_request.md":"DoEjoFLB","index.md":"Kqr-4KUQ","other_changelog.md":"Dz-zxRtD","plugins_demo.md":"CW-ex5pB","plugins_elements.md":"Ke7Ku4zw","plugins_index.md":"D99gd8Km","plugins_list.md":"BEhNXQHa","plugins_package.md":"BxdLSuv_","plugins_standard.md":"CZGtLnJm","start_faq.md":"DgVh5vn_","start_index.md":"BFHE9HXh","start_plugin.md":"CNhiew7Y","start_problems.md":"L4jIuoNc","start_render.md":"BE3g4IZU","start_start.md":"o7LsWNjd","utils_common.md":"DAm_feko","utils_index.md":"DWtjsB39","utils_karin.md":"CFqEbseG","utils_logger.md":"CGL38C-O","utils_redis.md":"D29mXVkq","utils_renderer.md":"sttYjLrQ","utils_segment.md":"CVqBqVai","utils_update.md":"Dh-Wa0_n","utils_yamleditor.md":"BZ_QBMZK"}
